taxus/__init__.py
taxus/likelihoods.py
taxus/models.py
taxus/tests.py
taxus/util.py
taxus-0.0.4.dist-info/WHEEL
taxus-0.0.4.dist-info/METADATA
taxus-0.0.4.dist-info/RECORD
